simplebox/__init__.py
simplebox/backend.py
simplebox/character.py
simplebox/classes.py
simplebox/cmd.py
simplebox/converter.py
simplebox/enums.py
simplebox/generic.py
simplebox/jsonparser.py
simplebox/lombok.py
simplebox/number.py
simplebox/serialize.py
simplebox/singleton.py
simplebox/sjson.py
simplebox/types.py
simplebox/version.py
simplebox/void.py
simplebox/_handler/__init__.py
simplebox/_handler/_backend_handler/__init__.py
simplebox/_handler/_backend_handler/_backend.py
simplebox/_handler/_backend_handler/_run.py
simplebox/_handler/_converter_handler/__init__.py
simplebox/_handler/_converter_handler/_calculator.py
simplebox/_handler/_method_handler/__init__.py
simplebox/_handler/_method_handler/_build_arguments.py
simplebox/_handler/_number_handler/__init__.py
simplebox/_handler/_number_handler/_compare.py
simplebox/_handler/_str_handler/__init__.py
simplebox/_handler/_str_handler/_strings.py
simplebox/_internal/__init__.py
simplebox/_internal/_argparse.py
simplebox/_internal/_banner.py
simplebox/_internal/_json_helper.py
simplebox/_internal/_lombok.py
simplebox/_internal/_serialization.py
simplebox/_internal/_tools.py
simplebox/_internal/_types.py
simplebox/_monkey/__init__.py
simplebox/_monkey/_requests.py
simplebox/_requests/__init__.py
simplebox/_requests/_adapter.py
simplebox/_requests/_models.py
simplebox/_requests/_utils.py
simplebox/_requests/_h2/__init__.py
simplebox/_requests/_h2/config.py
simplebox/_requests/_h2/connection.py
simplebox/_requests/_h2/errors.py
simplebox/_requests/_h2/events.py
simplebox/_requests/_h2/exceptions.py
simplebox/_requests/_h2/frame_buffer.py
simplebox/_requests/_h2/settings.py
simplebox/_requests/_h2/stream.py
simplebox/_requests/_h2/utilities.py
simplebox/_requests/_h2/windows.py
simplebox/_requests/_hpack/__init__.py
simplebox/_requests/_hpack/compat.py
simplebox/_requests/_hpack/exceptions.py
simplebox/_requests/_hpack/hpack.py
simplebox/_requests/_hpack/hpack_compat.py
simplebox/_requests/_hpack/huffman.py
simplebox-0.0.1a313.dist-info/METADATA
simplebox-0.0.1a313.dist-info/WHEEL
simplebox-0.0.1a313.dist-info/top_level.txt
simplebox-0.0.1a313.dist-info/RECORD
