Metadata-Version: 2.1
Name: simplebox
Version: 0.0.1a313
Summary: A simple tools box
Author: Galio
License: MIT Licence
Keywords: pip,simplebox,backend,fast,fasttools,box,simple
Platform: any
Requires-Python: >=3.9
Requires-Dist: psutil
Requires-Dist: requests
Requires-Dist: APScheduler
Requires-Dist: gevent
Requires-Dist: dataclasses-json (==0.5.7)
Requires-Dist: regex (==2022.10.31)
Requires-Dist: flameprof (==0.4)
Requires-Dist: jsonpath (==0.82)
Requires-Dist: orjson
Requires-Dist: rfc3986 (<2.0,>=1.1.0)
Requires-Dist: brotlipy (<1.0,>=0.7.0)
Requires-Dist: service-identity (==24.1.0)
Requires-Dist: pyOpenSSL (==24.1.0)
Requires-Dist: DBUtils (==3.1.0)
Requires-Dist: pymysql (==1.1.0)
Requires-Dist: sqlalchemy (==2.0.29)
Requires-Dist: cx-Oracle (==8.3.0)
Requires-Dist: pycryptodome (==3.20.0)
Requires-Dist: multipledispatch (>=1.0.0)
Requires-Dist: fasteners (==0.19)
Requires-Dist: requests-toolbelt
Requires-Dist: openpyxl
Requires-Dist: python-dateutil
